{"traceEvents": [{"name": "dpu_alloc", "cat": "dpu", "pid": 6092, "tid": 6092, "ts": 4115471919.715, "ph": "B", "args": {"perf_period": 1, "common_pid": 6092, "common_preempt_count": 0, "common_type": 5108, "_probe_ip": 139633561301456, "perf_pid": 6092, "perf_ip": 139633561301456, "common_flags": 0, "perf_callchain": [18446744073709551104, 139633561301456, 4333543705419175690], "profile": 0, "dpu_set": 140728643985592, "nr_dpus": 2543, "perf_callchain_size": 3, "perf_tid": 6092, "perf_id": 112170}}, {"cat": "dpu", "pid": 6092, "tid": 6092, "ts": 4115605136.395, "ph": "E", "args": {"perf_period": 1, "_probe_ret_ip": 4199308, "_probe_func": 139633561301456, "common_pid": 6092, "common_preempt_count": 0, "common_type": 5109, "perf_pid": 6092, "perf_ip": 4199308, "common_flags": 0, "perf_callchain": [18446744073709551104, 4199308, 4333543705419175690], "perf_callchain_size": 3, "perf_tid": 6092, "perf_id": 112204}}, {"name": "dpu_load", "cat": "dpu", "pid": 6092, "tid": 6092, "ts": 4115605179.392, "ph": "B", "args": {"perf_period": 1, "program": 0, "common_pid": 6092, "common_preempt_count": 0, "common_type": 5094, "_probe_ip": 139633561298432, "perf_pid": 6092, "binary_path": 4207102, "perf_ip": 139633561298432, "common_flags": 0, "perf_callchain": [18446744073709551104, 139633561298432, 4333543705419175690], "dpu_set": 0, "perf_callchain_size": 3, "perf_tid": 6092, "perf_id": 111724}}, {"cat": "dpu", "pid": 6092, "tid": 6092, "ts": 4115656882.618, "ph": "E", "args": {"perf_period": 1, "_probe_ret_ip": 4199575, "_probe_func": 139633561298432, "common_pid": 6092, "common_preempt_count": 0, "common_type": 5095, "perf_pid": 6092, "perf_ip": 4199575, "common_flags": 0, "perf_callchain": [18446744073709551104, 4199575, 4333543705419175690], "perf_callchain_size": 3, "perf_tid": 6092, "perf_id": 111756}}, {"name": "dpu_push_xfer", "cat": "dpu", "pid": 6092, "tid": 6092, "ts": 4115664204.559, "ph": "B", "args": {"perf_period": 1, "symbol_name": 4207088, "common_pid": 6092, "common_preempt_count": 0, "flags": 0, "perf_id": 112364, "common_type": 5114, "_probe_ip": 139633561316784, "xfer": 0, "perf_pid": 6092, "symbol_offset": 0, "perf_ip": 139633561316784, "common_flags": 0, "perf_callchain": [18446744073709551104, 139633561316784, 171798691880, 40], "dpu_set": 0, "perf_callchain_size": 4, "perf_tid": 6092, "length": 1344}}, {"cat": "dpu", "pid": 6092, "tid": 6092, "ts": 4115675250.362, "ph": "E", "args": {"perf_period": 1, "_probe_ret_ip": 4200166, "_probe_func": 139633561316784, "common_pid": 6092, "common_preempt_count": 0, "common_type": 5115, "perf_pid": 6092, "perf_ip": 4200166, "common_flags": 0, "perf_callchain": [18446744073709551104, 4200166, 171798691880, 40], "perf_callchain_size": 4, "perf_tid": 6092, "perf_id": 112396}}, {"name": "dpu_push_xfer", "cat": "dpu", "pid": 6092, "tid": 6092, "ts": 4115675322.557, "ph": "B", "args": {"perf_period": 1, "symbol_name": 4207092, "common_pid": 6092, "common_preempt_count": 0, "flags": 0, "perf_id": 112364, "common_type": 5114, "_probe_ip": 139633561316784, "xfer": 0, "perf_pid": 6092, "symbol_offset": 0, "perf_ip": 139633561316784, "common_flags": 0, "perf_callchain": [18446744073709551104, 139633561316784, 171798691880, 40], "dpu_set": 0, "perf_callchain_size": 4, "perf_tid": 6092, "length": 43008}}, {"cat": "dpu", "pid": 6092, "tid": 6092, "ts": 4115924248.485, "ph": "E", "args": {"perf_period": 1, "_probe_ret_ip": 4200326, "_probe_func": 139633561316784, "common_pid": 6092, "common_preempt_count": 0, "common_type": 5115, "perf_pid": 6092, "perf_ip": 4200326, "common_flags": 0, "perf_callchain": [18446744073709551104, 4200326, 171798691880, 40], "perf_callchain_size": 4, "perf_tid": 6092, "perf_id": 112396}}, {"name": "dpu_launch", "cat": "dpu", "pid": 6092, "tid": 6092, "ts": 4115924254.569, "ph": "B", "args": {"perf_period": 1, "common_pid": 6092, "common_preempt_count": 0, "policy": 1, "common_type": 5100, "_probe_ip": 139633561298560, "perf_pid": 6092, "perf_ip": 139633561298560, "common_flags": 0, "perf_callchain": [18446744073709551104, 139633561298560, 171798691880, 40], "dpu_set": 139633545228304, "perf_callchain_size": 4, "perf_tid": 6092, "perf_id": 111916}}, {"cat": "dpu", "pid": 6092, "tid": 6092, "ts": 4115950906.972, "ph": "E", "args": {"perf_period": 1, "_probe_ret_ip": 4200361, "_probe_func": 139633561298560, "common_pid": 6092, "common_preempt_count": 0, "common_type": 5101, "perf_pid": 6092, "perf_ip": 4200361, "common_flags": 0, "perf_callchain": [18446744073709551104, 4200361, 171798691880, 40], "perf_callchain_size": 4, "perf_tid": 6092, "perf_id": 111948}}, {"name": "dpu_push_xfer", "cat": "dpu", "pid": 6092, "tid": 6092, "ts": 4115950985.535, "ph": "B", "args": {"perf_period": 1, "symbol_name": 4207097, "common_pid": 6092, "common_preempt_count": 0, "flags": 0, "perf_id": 112364, "common_type": 5114, "_probe_ip": 139633561316784, "xfer": 1, "perf_pid": 6092, "symbol_offset": 0, "perf_ip": 139633561316784, "common_flags": 0, "perf_callchain": [18446744073709551104, 139633561316784, 171798691880, 40], "dpu_set": 0, "perf_callchain_size": 4, "perf_tid": 6092, "length": 1152}}, {"cat": "dpu", "pid": 6092, "tid": 6092, "ts": 4115965299.301, "ph": "E", "args": {"perf_period": 1, "_probe_ret_ip": 4200548, "_probe_func": 139633561316784, "common_pid": 6092, "common_preempt_count": 0, "common_type": 5115, "perf_pid": 6092, "perf_ip": 4200548, "common_flags": 0, "perf_callchain": [18446744073709551104, 4200548, 171798691880, 40], "perf_callchain_size": 4, "perf_tid": 6092, "perf_id": 112396}}, {"name": "dpu_load", "cat": "dpu", "pid": 6092, "tid": 6092, "ts": 4116114644.345, "ph": "B", "args": {"perf_period": 1, "program": 0, "common_pid": 6092, "common_preempt_count": 0, "common_type": 5094, "_probe_ip": 139633561298432, "perf_pid": 6092, "binary_path": 4207125, "perf_ip": 139633561298432, "common_flags": 0, "perf_callchain": [18446744073709551104, 139633561298432, 4333543705419175690], "dpu_set": 0, "perf_callchain_size": 3, "perf_tid": 6092, "perf_id": 111724}}, {"cat": "dpu", "pid": 6092, "tid": 6092, "ts": 4116145208.606, "ph": "E", "args": {"perf_period": 1, "_probe_ret_ip": 4201335, "_probe_func": 139633561298432, "common_pid": 6092, "common_preempt_count": 0, "common_type": 5095, "perf_pid": 6092, "perf_ip": 4201335, "common_flags": 0, "perf_callchain": [18446744073709551104, 4201335, 4333543705419175690], "perf_callchain_size": 3, "perf_tid": 6092, "perf_id": 111756}}, {"name": "dpu_push_xfer", "cat": "dpu", "pid": 6092, "tid": 6092, "ts": 4116149631.922, "ph": "B", "args": {"perf_period": 1, "symbol_name": 4207097, "common_pid": 6092, "common_preempt_count": 0, "flags": 0, "perf_id": 112364, "common_type": 5114, "_probe_ip": 139633561316784, "xfer": 0, "perf_pid": 6092, "symbol_offset": 0, "perf_ip": 139633561316784, "common_flags": 0, "perf_callchain": [18446744073709551104, 139633561316784, 171798691880, 40], "dpu_set": 0, "perf_callchain_size": 4, "perf_tid": 6092, "length": 1152}}, {"cat": "dpu", "pid": 6092, "tid": 6092, "ts": 4116160319.444, "ph": "E", "args": {"perf_period": 1, "_probe_ret_ip": 4201958, "_probe_func": 139633561316784, "common_pid": 6092, "common_preempt_count": 0, "common_type": 5115, "perf_pid": 6092, "perf_ip": 4201958, "common_flags": 0, "perf_callchain": [18446744073709551104, 4201958, 171798691880, 40], "perf_callchain_size": 4, "perf_tid": 6092, "perf_id": 112396}}, {"name": "dpu_push_xfer", "cat": "dpu", "pid": 6092, "tid": 6092, "ts": 4116160482.953, "ph": "B", "args": {"perf_period": 1, "symbol_name": 4207115, "common_pid": 6092, "common_preempt_count": 0, "flags": 0, "perf_id": 112364, "common_type": 5114, "_probe_ip": 139633561316784, "xfer": 0, "perf_pid": 6092, "symbol_offset": 0, "perf_ip": 139633561316784, "common_flags": 0, "perf_callchain": [18446744073709551104, 139633561316784, 171798691880, 40], "dpu_set": 0, "perf_callchain_size": 4, "perf_tid": 6092, "length": 24576}}, {"cat": "dpu", "pid": 6092, "tid": 6092, "ts": 4116308108.935, "ph": "E", "args": {"perf_period": 1, "_probe_ret_ip": 4202118, "_probe_func": 139633561316784, "common_pid": 6092, "common_preempt_count": 0, "common_type": 5115, "perf_pid": 6092, "perf_ip": 4202118, "common_flags": 0, "perf_callchain": [18446744073709551104, 4202118, 171798691880, 40], "perf_callchain_size": 4, "perf_tid": 6092, "perf_id": 112396}}, {"name": "dpu_launch", "cat": "dpu", "pid": 6092, "tid": 6092, "ts": 4116308112.25, "ph": "B", "args": {"perf_period": 1, "common_pid": 6092, "common_preempt_count": 0, "policy": 1, "common_type": 5100, "_probe_ip": 139633561298560, "perf_pid": 6092, "perf_ip": 139633561298560, "common_flags": 0, "perf_callchain": [18446744073709551104, 139633561298560, 171798691880, 40], "dpu_set": 139633543274512, "perf_callchain_size": 4, "perf_tid": 6092, "perf_id": 111916}}, {"cat": "dpu", "pid": 6092, "tid": 6092, "ts": 4116323015.695, "ph": "E", "args": {"perf_period": 1, "_probe_ret_ip": 4202153, "_probe_func": 139633561298560, "common_pid": 6092, "common_preempt_count": 0, "common_type": 5101, "perf_pid": 6092, "perf_ip": 4202153, "common_flags": 0, "perf_callchain": [18446744073709551104, 4202153, 171798691880, 40], "perf_callchain_size": 4, "perf_tid": 6092, "perf_id": 111948}}, {"name": "dpu_push_xfer", "cat": "dpu", "pid": 6092, "tid": 6092, "ts": 4116323105.256, "ph": "B", "args": {"perf_period": 1, "symbol_name": 4207120, "common_pid": 6092, "common_preempt_count": 0, "flags": 0, "perf_id": 112364, "common_type": 5114, "_probe_ip": 139633561316784, "xfer": 1, "perf_pid": 6092, "symbol_offset": 0, "perf_ip": 139633561316784, "common_flags": 0, "perf_callchain": [18446744073709551104, 139633561316784, 171798691880, 40], "dpu_set": 0, "perf_callchain_size": 4, "perf_tid": 6092, "length": 768}}, {"cat": "dpu", "pid": 6092, "tid": 6092, "ts": 4116330193.955, "ph": "E", "args": {"perf_period": 1, "_probe_ret_ip": 4202340, "_probe_func": 139633561316784, "common_pid": 6092, "common_preempt_count": 0, "common_type": 5115, "perf_pid": 6092, "perf_ip": 4202340, "common_flags": 0, "perf_callchain": [18446744073709551104, 4202340, 171798691880, 40], "perf_callchain_size": 4, "perf_tid": 6092, "perf_id": 112396}}, {"name": "dpu_load", "cat": "dpu", "pid": 6092, "tid": 6092, "ts": 4116431540.073, "ph": "B", "args": {"perf_period": 1, "program": 0, "common_pid": 6092, "common_preempt_count": 0, "common_type": 5094, "_probe_ip": 139633561298432, "perf_pid": 6092, "binary_path": 4207151, "perf_ip": 139633561298432, "common_flags": 0, "perf_callchain": [18446744073709551104, 139633561298432, 6075149511265903986], "dpu_set": 0, "perf_callchain_size": 3, "perf_tid": 6092, "perf_id": 111724}}, {"cat": "dpu", "pid": 6092, "tid": 6092, "ts": 4116440706.397, "ph": "E", "args": {"perf_period": 1, "_probe_ret_ip": 4203127, "_probe_func": 139633561298432, "common_pid": 6092, "common_preempt_count": 0, "common_type": 5095, "perf_pid": 6092, "perf_ip": 4203127, "common_flags": 0, "perf_callchain": [18446744073709551104, 4203127, 6075149511265903986], "perf_callchain_size": 3, "perf_tid": 6092, "perf_id": 111756}}, {"name": "dpu_push_xfer", "cat": "dpu", "pid": 6092, "tid": 6092, "ts": 4116442183.813, "ph": "B", "args": {"perf_period": 1, "symbol_name": 4207120, "common_pid": 6092, "common_preempt_count": 0, "flags": 0, "perf_id": 112364, "common_type": 5114, "_probe_ip": 139633561316784, "xfer": 0, "perf_pid": 6092, "symbol_offset": 0, "perf_ip": 139633561316784, "common_flags": 0, "perf_callchain": [18446744073709551104, 139633561316784, 171798691880, 40], "dpu_set": 0, "perf_callchain_size": 4, "perf_tid": 6092, "length": 768}}, {"cat": "dpu", "pid": 6092, "tid": 6092, "ts": 4116451468.069, "ph": "E", "args": {"perf_period": 1, "_probe_ret_ip": 4203611, "_probe_func": 139633561316784, "common_pid": 6092, "common_preempt_count": 0, "common_type": 5115, "perf_pid": 6092, "perf_ip": 4203611, "common_flags": 0, "perf_callchain": [18446744073709551104, 4203611, 171798691880, 40], "perf_callchain_size": 4, "perf_tid": 6092, "perf_id": 112396}}, {"name": "dpu_push_xfer", "cat": "dpu", "pid": 6092, "tid": 6092, "ts": 4116451548.791, "ph": "B", "args": {"perf_period": 1, "symbol_name": 4207139, "common_pid": 6092, "common_preempt_count": 0, "flags": 0, "perf_id": 112364, "common_type": 5114, "_probe_ip": 139633561316784, "xfer": 0, "perf_pid": 6092, "symbol_offset": 0, "perf_ip": 139633561316784, "common_flags": 0, "perf_callchain": [18446744073709551104, 139633561316784, 171798691880, 40], "dpu_set": 0, "perf_callchain_size": 4, "perf_tid": 6092, "length": 256}}, {"cat": "dpu", "pid": 6092, "tid": 6092, "ts": 4116454497.073, "ph": "E", "args": {"perf_period": 1, "_probe_ret_ip": 4203787, "_probe_func": 139633561316784, "common_pid": 6092, "common_preempt_count": 0, "common_type": 5115, "perf_pid": 6092, "perf_ip": 4203787, "common_flags": 0, "perf_callchain": [18446744073709551104, 4203787, 171798691880, 40], "perf_callchain_size": 4, "perf_tid": 6092, "perf_id": 112396}}, {"name": "dpu_launch", "cat": "dpu", "pid": 6092, "tid": 6092, "ts": 4116454500.624, "ph": "B", "args": {"perf_period": 1, "common_pid": 6092, "common_preempt_count": 0, "policy": 1, "common_type": 5100, "_probe_ip": 139633561298560, "perf_pid": 6092, "perf_ip": 139633561298560, "common_flags": 0, "perf_callchain": [18446744073709551104, 139633561298560, 171798691880, 40], "dpu_set": 19486624, "perf_callchain_size": 4, "perf_tid": 6092, "perf_id": 111916}}, {"cat": "dpu", "pid": 6092, "tid": 6092, "ts": 4116455721.811, "ph": "E", "args": {"perf_period": 1, "_probe_ret_ip": 4203821, "_probe_func": 139633561298560, "common_pid": 6092, "common_preempt_count": 0, "common_type": 5101, "perf_pid": 6092, "perf_ip": 4203821, "common_flags": 0, "perf_callchain": [18446744073709551104, 4203821, 171798691880, 40], "perf_callchain_size": 4, "perf_tid": 6092, "perf_id": 111948}}, {"name": "dpu_push_xfer", "cat": "dpu", "pid": 6092, "tid": 6092, "ts": 4116455805.208, "ph": "B", "args": {"perf_period": 1, "symbol_name": 4207144, "common_pid": 6092, "common_preempt_count": 0, "flags": 0, "perf_id": 112364, "common_type": 5114, "_probe_ip": 139633561316784, "xfer": 1, "perf_pid": 6092, "symbol_offset": 0, "perf_ip": 139633561316784, "common_flags": 0, "perf_callchain": [18446744073709551104, 139633561316784, 171798691880, 40], "dpu_set": 0, "perf_callchain_size": 4, "perf_tid": 6092, "length": 12}}, {"cat": "dpu", "pid": 6092, "tid": 6092, "ts": 4116456168.113, "ph": "E", "args": {"perf_period": 1, "_probe_ret_ip": 4204006, "_probe_func": 139633561316784, "common_pid": 6092, "common_preempt_count": 0, "common_type": 5115, "perf_pid": 6092, "perf_ip": 4204006, "common_flags": 0, "perf_callchain": [18446744073709551104, 4204006, 171798691880, 40], "perf_callchain_size": 4, "perf_tid": 6092, "perf_id": 112396}}]}