{"traceEvents": [{"name": "dpu_alloc", "cat": "dpu", "pid": 6826, "tid": 6826, "ts": 21863048202.024, "ph": "B", "args": {"perf_period": 1, "common_flags": 0, "dpu_set": 140725194131736, "perf_id": 190873, "nr_dpus": 2556, "perf_callchain": [18446744073709551104, 140708768350672, 8589934594], "common_type": 7554, "_probe_ip": 140708768350672, "perf_callchain_size": 3, "perf_tid": 6826, "perf_ip": 140708768350672, "common_pid": 6826, "perf_pid": 6826, "common_preempt_count": 0, "profile": 0}}, {"cat": "dpu", "pid": 6826, "tid": 6826, "ts": 21863204002.763, "ph": "E", "args": {"_probe_func": 140708768350672, "perf_period": 1, "_probe_ret_ip": 4199308, "common_flags": 0, "perf_id": 190905, "perf_callchain": [18446744073709551104, 4199308, 8589934594], "common_type": 7555, "perf_callchain_size": 3, "perf_tid": 6826, "perf_ip": 4199308, "common_pid": 6826, "perf_pid": 6826, "common_preempt_count": 0}}, {"name": "dpu_load", "cat": "dpu", "pid": 6826, "tid": 6826, "ts": 21863204034.958, "ph": "B", "args": {"perf_period": 1, "common_flags": 0, "program": 0, "dpu_set": 0, "perf_id": 190425, "perf_callchain": [18446744073709551104, 140708768347648, 8589934594], "common_type": 7540, "_probe_ip": 140708768347648, "perf_callchain_size": 3, "perf_tid": 6826, "binary_path": 4207061, "perf_ip": 140708768347648, "common_pid": 6826, "perf_pid": 6826, "common_preempt_count": 0}}, {"cat": "dpu", "pid": 6826, "tid": 6826, "ts": 21863256896.435, "ph": "E", "args": {"_probe_func": 140708768347648, "perf_period": 1, "_probe_ret_ip": 4199575, "common_flags": 0, "perf_id": 190457, "perf_callchain": [18446744073709551104, 4199575, 8589934594], "common_type": 7541, "perf_callchain_size": 3, "perf_tid": 6826, "perf_ip": 4199575, "common_pid": 6826, "perf_pid": 6826, "common_preempt_count": 0}}, {"name": "dpu_push_xfer", "cat": "dpu", "pid": 6826, "tid": 6826, "ts": 21863260890.955, "ph": "B", "args": {"perf_period": 1, "common_flags": 0, "flags": 0, "dpu_set": 0, "perf_id": 191065, "xfer": 0, "perf_callchain": [18446744073709551104, 140708768366000, 171798691880, 40], "common_type": 7560, "_probe_ip": 140708768366000, "symbol_name": 4207047, "perf_callchain_size": 4, "length": 2112, "symbol_offset": 0, "perf_tid": 6826, "perf_ip": 140708768366000, "common_pid": 6826, "perf_pid": 6826, "common_preempt_count": 0}}, {"cat": "dpu", "pid": 6826, "tid": 6826, "ts": 21863279576.832, "ph": "E", "args": {"_probe_func": 140708768366000, "perf_period": 1, "_probe_ret_ip": 4200166, "common_flags": 0, "perf_id": 191097, "perf_callchain": [18446744073709551104, 4200166, 171798691880, 40], "common_type": 7561, "perf_callchain_size": 4, "perf_tid": 6826, "perf_ip": 4200166, "common_pid": 6826, "perf_pid": 6826, "common_preempt_count": 0}}, {"name": "dpu_push_xfer", "cat": "dpu", "pid": 6826, "tid": 6826, "ts": 21863279668.777, "ph": "B", "args": {"perf_period": 1, "common_flags": 0, "flags": 0, "dpu_set": 0, "perf_id": 191065, "xfer": 0, "perf_callchain": [18446744073709551104, 140708768366000, 171798691880, 40], "common_type": 7560, "_probe_ip": 140708768366000, "symbol_name": 4207051, "perf_callchain_size": 4, "length": 45056, "symbol_offset": 0, "perf_tid": 6826, "perf_ip": 140708768366000, "common_pid": 6826, "perf_pid": 6826, "common_preempt_count": 0}}, {"cat": "dpu", "pid": 6826, "tid": 6826, "ts": 21863581456.719, "ph": "E", "args": {"_probe_func": 140708768366000, "perf_period": 1, "_probe_ret_ip": 4200326, "common_flags": 0, "perf_id": 191097, "perf_callchain": [18446744073709551104, 4200326, 171798691880, 40], "common_type": 7561, "perf_callchain_size": 4, "perf_tid": 6826, "perf_ip": 4200326, "common_pid": 6826, "perf_pid": 6826, "common_preempt_count": 0}}, {"name": "dpu_launch", "cat": "dpu", "pid": 6826, "tid": 6826, "ts": 21863581466.963, "ph": "B", "args": {"perf_period": 1, "common_flags": 0, "dpu_set": 140708751265808, "perf_id": 190617, "perf_callchain": [18446744073709551104, 140708768347776, 171798691880, 40], "common_type": 7546, "_probe_ip": 140708768347776, "perf_callchain_size": 4, "perf_tid": 6826, "policy": 1, "perf_ip": 140708768347776, "common_pid": 6826, "perf_pid": 6826, "common_preempt_count": 0}}, {"cat": "dpu", "pid": 6826, "tid": 6826, "ts": 21863584943.535, "ph": "E", "args": {"_probe_func": 140708768347776, "perf_period": 1, "_probe_ret_ip": 4200361, "common_flags": 0, "perf_id": 190649, "perf_callchain": [18446744073709551104, 4200361, 171798691880, 40], "common_type": 7547, "perf_callchain_size": 4, "perf_tid": 6826, "perf_ip": 4200361, "common_pid": 6826, "perf_pid": 6826, "common_preempt_count": 0}}, {"name": "dpu_push_xfer", "cat": "dpu", "pid": 6826, "tid": 6826, "ts": 21863585189.798, "ph": "B", "args": {"perf_period": 1, "common_flags": 0, "flags": 0, "dpu_set": 0, "perf_id": 191065, "xfer": 1, "perf_callchain": [18446744073709551104, 140708768366000, 171798691880, 40], "common_type": 7560, "_probe_ip": 140708768366000, "symbol_name": 4207056, "perf_callchain_size": 4, "length": 768, "symbol_offset": 0, "perf_tid": 6826, "perf_ip": 140708768366000, "common_pid": 6826, "perf_pid": 6826, "common_preempt_count": 0}}, {"cat": "dpu", "pid": 6826, "tid": 6826, "ts": 21863591968.092, "ph": "E", "args": {"_probe_func": 140708768366000, "perf_period": 1, "_probe_ret_ip": 4200546, "common_flags": 0, "perf_id": 191097, "perf_callchain": [18446744073709551104, 4200546, 171798691880, 40], "common_type": 7561, "perf_callchain_size": 4, "perf_tid": 6826, "perf_ip": 4200546, "common_pid": 6826, "perf_pid": 6826, "common_preempt_count": 0}}, {"name": "dpu_load", "cat": "dpu", "pid": 6826, "tid": 6826, "ts": 21863658776.094, "ph": "B", "args": {"perf_period": 1, "common_flags": 0, "program": 0, "dpu_set": 0, "perf_id": 190425, "perf_callchain": [18446744073709551104, 140708768347648, 8589934594], "common_type": 7540, "_probe_ip": 140708768347648, "perf_callchain_size": 3, "perf_tid": 6826, "binary_path": 4207081, "perf_ip": 140708768347648, "common_pid": 6826, "perf_pid": 6826, "common_preempt_count": 0}}, {"cat": "dpu", "pid": 6826, "tid": 6826, "ts": 21863684754.152, "ph": "E", "args": {"_probe_func": 140708768347648, "perf_period": 1, "_probe_ret_ip": 4201319, "common_flags": 0, "perf_id": 190457, "perf_callchain": [18446744073709551104, 4201319, 8589934594], "common_type": 7541, "perf_callchain_size": 3, "perf_tid": 6826, "perf_ip": 4201319, "common_pid": 6826, "perf_pid": 6826, "common_preempt_count": 0}}, {"name": "dpu_push_xfer", "cat": "dpu", "pid": 6826, "tid": 6826, "ts": 21863687321.886, "ph": "B", "args": {"perf_period": 1, "common_flags": 0, "flags": 0, "dpu_set": 0, "perf_id": 191065, "xfer": 0, "perf_callchain": [18446744073709551104, 140708768366000, 171798691880, 40], "common_type": 7560, "_probe_ip": 140708768366000, "symbol_name": 4207056, "perf_callchain_size": 4, "length": 768, "symbol_offset": 0, "perf_tid": 6826, "perf_ip": 140708768366000, "common_pid": 6826, "perf_pid": 6826, "common_preempt_count": 0}}, {"cat": "dpu", "pid": 6826, "tid": 6826, "ts": 21863694402.926, "ph": "E", "args": {"_probe_func": 140708768366000, "perf_period": 1, "_probe_ret_ip": 4201910, "common_flags": 0, "perf_id": 191097, "perf_callchain": [18446744073709551104, 4201910, 171798691880, 40], "common_type": 7561, "perf_callchain_size": 4, "perf_tid": 6826, "perf_ip": 4201910, "common_pid": 6826, "perf_pid": 6826, "common_preempt_count": 0}}, {"name": "dpu_push_xfer", "cat": "dpu", "pid": 6826, "tid": 6826, "ts": 21863694512.982, "ph": "B", "args": {"perf_period": 1, "common_flags": 0, "flags": 0, "dpu_set": 0, "perf_id": 191065, "xfer": 0, "perf_callchain": [18446744073709551104, 140708768366000, 171798691880, 40], "common_type": 7560, "_probe_ip": 140708768366000, "symbol_name": 4207071, "perf_callchain_size": 4, "length": 16384, "symbol_offset": 0, "perf_tid": 6826, "perf_ip": 140708768366000, "common_pid": 6826, "perf_pid": 6826, "common_preempt_count": 0}}, {"cat": "dpu", "pid": 6826, "tid": 6826, "ts": 21863816963.355, "ph": "E", "args": {"_probe_func": 140708768366000, "perf_period": 1, "_probe_ret_ip": 4202070, "common_flags": 0, "perf_id": 191097, "perf_callchain": [18446744073709551104, 4202070, 171798691880, 40], "common_type": 7561, "perf_callchain_size": 4, "perf_tid": 6826, "perf_ip": 4202070, "common_pid": 6826, "perf_pid": 6826, "common_preempt_count": 0}}, {"name": "dpu_launch", "cat": "dpu", "pid": 6826, "tid": 6826, "ts": 21863816968.062, "ph": "B", "args": {"perf_period": 1, "common_flags": 0, "dpu_set": 140708749299728, "perf_id": 190617, "perf_callchain": [18446744073709551104, 140708768347776, 171798691880, 40], "common_type": 7546, "_probe_ip": 140708768347776, "perf_callchain_size": 4, "perf_tid": 6826, "policy": 1, "perf_ip": 140708768347776, "common_pid": 6826, "perf_pid": 6826, "common_preempt_count": 0}}, {"cat": "dpu", "pid": 6826, "tid": 6826, "ts": 21863818419.918, "ph": "E", "args": {"_probe_func": 140708768347776, "perf_period": 1, "_probe_ret_ip": 4202105, "common_flags": 0, "perf_id": 190649, "perf_callchain": [18446744073709551104, 4202105, 171798691880, 40], "common_type": 7547, "perf_callchain_size": 4, "perf_tid": 6826, "perf_ip": 4202105, "common_pid": 6826, "perf_pid": 6826, "common_preempt_count": 0}}, {"name": "dpu_push_xfer", "cat": "dpu", "pid": 6826, "tid": 6826, "ts": 21863818568.62, "ph": "B", "args": {"perf_period": 1, "common_flags": 0, "flags": 0, "dpu_set": 0, "perf_id": 191065, "xfer": 1, "perf_callchain": [18446744073709551104, 140708768366000, 171798691880, 40], "common_type": 7560, "_probe_ip": 140708768366000, "symbol_name": 4207076, "perf_callchain_size": 4, "length": 768, "symbol_offset": 0, "perf_tid": 6826, "perf_ip": 140708768366000, "common_pid": 6826, "perf_pid": 6826, "common_preempt_count": 0}}, {"cat": "dpu", "pid": 6826, "tid": 6826, "ts": 21863826173.532, "ph": "E", "args": {"_probe_func": 140708768366000, "perf_period": 1, "_probe_ret_ip": 4202290, "common_flags": 0, "perf_id": 191097, "perf_callchain": [18446744073709551104, 4202290, 171798691880, 40], "common_type": 7561, "perf_callchain_size": 4, "perf_tid": 6826, "perf_ip": 4202290, "common_pid": 6826, "perf_pid": 6826, "common_preempt_count": 0}}, {"name": "dpu_load", "cat": "dpu", "pid": 6826, "tid": 6826, "ts": 21863892319.478, "ph": "B", "args": {"perf_period": 1, "common_flags": 0, "program": 0, "dpu_set": 0, "perf_id": 190425, "perf_callchain": [18446744073709551104, 140708768347648, 6075149511265903986], "common_type": 7540, "_probe_ip": 140708768347648, "perf_callchain_size": 3, "perf_tid": 6826, "binary_path": 4207104, "perf_ip": 140708768347648, "common_pid": 6826, "perf_pid": 6826, "common_preempt_count": 0}}, {"cat": "dpu", "pid": 6826, "tid": 6826, "ts": 21863896512.424, "ph": "E", "args": {"_probe_func": 140708768347648, "perf_period": 1, "_probe_ret_ip": 4203063, "common_flags": 0, "perf_id": 190457, "perf_callchain": [18446744073709551104, 4203063, 6075149511265903986], "common_type": 7541, "perf_callchain_size": 3, "perf_tid": 6826, "perf_ip": 4203063, "common_pid": 6826, "perf_pid": 6826, "common_preempt_count": 0}}, {"name": "dpu_push_xfer", "cat": "dpu", "pid": 6826, "tid": 6826, "ts": 21863897919.439, "ph": "B", "args": {"perf_period": 1, "common_flags": 0, "flags": 0, "dpu_set": 0, "perf_id": 191065, "xfer": 0, "perf_callchain": [18446744073709551104, 140708768366000, 171798691880, 40], "common_type": 7560, "_probe_ip": 140708768366000, "symbol_name": 4207076, "perf_callchain_size": 4, "length": 768, "symbol_offset": 0, "perf_tid": 6826, "perf_ip": 140708768366000, "common_pid": 6826, "perf_pid": 6826, "common_preempt_count": 0}}, {"cat": "dpu", "pid": 6826, "tid": 6826, "ts": 21863909480.354, "ph": "E", "args": {"_probe_func": 140708768366000, "perf_period": 1, "_probe_ret_ip": 4203515, "common_flags": 0, "perf_id": 191097, "perf_callchain": [18446744073709551104, 4203515, 171798691880, 40], "common_type": 7561, "perf_callchain_size": 4, "perf_tid": 6826, "perf_ip": 4203515, "common_pid": 6826, "perf_pid": 6826, "common_preempt_count": 0}}, {"name": "dpu_push_xfer", "cat": "dpu", "pid": 6826, "tid": 6826, "ts": 21863909565.155, "ph": "B", "args": {"perf_period": 1, "common_flags": 0, "flags": 0, "dpu_set": 0, "perf_id": 191065, "xfer": 0, "perf_callchain": [18446744073709551104, 140708768366000, 171798691880, 40], "common_type": 7560, "_probe_ip": 140708768366000, "symbol_name": 4207092, "perf_callchain_size": 4, "length": 256, "symbol_offset": 0, "perf_tid": 6826, "perf_ip": 140708768366000, "common_pid": 6826, "perf_pid": 6826, "common_preempt_count": 0}}, {"cat": "dpu", "pid": 6826, "tid": 6826, "ts": 21863913233.591, "ph": "E", "args": {"_probe_func": 140708768366000, "perf_period": 1, "_probe_ret_ip": 4203691, "common_flags": 0, "perf_id": 191097, "perf_callchain": [18446744073709551104, 4203691, 171798691880, 40], "common_type": 7561, "perf_callchain_size": 4, "perf_tid": 6826, "perf_ip": 4203691, "common_pid": 6826, "perf_pid": 6826, "common_preempt_count": 0}}, {"name": "dpu_launch", "cat": "dpu", "pid": 6826, "tid": 6826, "ts": 21863913237.175, "ph": "B", "args": {"perf_period": 1, "common_flags": 0, "dpu_set": 4874144, "perf_id": 190617, "perf_callchain": [18446744073709551104, 140708768347776, 171798691880, 40], "common_type": 7546, "_probe_ip": 140708768347776, "perf_callchain_size": 4, "perf_tid": 6826, "policy": 1, "perf_ip": 140708768347776, "common_pid": 6826, "perf_pid": 6826, "common_preempt_count": 0}}, {"cat": "dpu", "pid": 6826, "tid": 6826, "ts": 21863913763.14, "ph": "E", "args": {"_probe_func": 140708768347776, "perf_period": 1, "_probe_ret_ip": 4203725, "common_flags": 0, "perf_id": 190649, "perf_callchain": [18446744073709551104, 4203725, 171798691880, 40], "common_type": 7547, "perf_callchain_size": 4, "perf_tid": 6826, "perf_ip": 4203725, "common_pid": 6826, "perf_pid": 6826, "common_preempt_count": 0}}, {"name": "dpu_push_xfer", "cat": "dpu", "pid": 6826, "tid": 6826, "ts": 21863913872.057, "ph": "B", "args": {"perf_period": 1, "common_flags": 0, "flags": 0, "dpu_set": 0, "perf_id": 191065, "xfer": 1, "perf_callchain": [18446744073709551104, 140708768366000, 171798691880, 40], "common_type": 7560, "_probe_ip": 140708768366000, "symbol_name": 4207097, "perf_callchain_size": 4, "length": 12, "symbol_offset": 0, "perf_tid": 6826, "perf_ip": 140708768366000, "common_pid": 6826, "perf_pid": 6826, "common_preempt_count": 0}}, {"cat": "dpu", "pid": 6826, "tid": 6826, "ts": 21863914289.33, "ph": "E", "args": {"_probe_func": 140708768366000, "perf_period": 1, "_probe_ret_ip": 4203910, "common_flags": 0, "perf_id": 191097, "perf_callchain": [18446744073709551104, 4203910, 171798691880, 40], "common_type": 7561, "perf_callchain_size": 4, "perf_tid": 6826, "perf_ip": 4203910, "common_pid": 6826, "perf_pid": 6826, "common_preempt_count": 0}}]}