{"traceEvents": [{"name": "dpu_alloc", "cat": "dpu", "pid": 21672, "tid": 21672, "ts": 4831205330.634, "ph": "B", "args": {"perf_period": 1, "common_type": 7228, "perf_pid": 21672, "common_pid": 21672, "common_flags": 0, "dpu_set": 140721397719416, "perf_ip": 140159886098896, "perf_id": 180181, "profile": 0, "_probe_ip": 140159886098896, "perf_callchain_size": 3, "perf_callchain": [18446744073709551104, 140159886098896, 4333543705419175690], "common_preempt_count": 0, "perf_tid": 21672, "nr_dpus": 2543}}, {"cat": "dpu", "pid": 21672, "tid": 21672, "ts": 4831326718.807, "ph": "E", "args": {"_probe_func": 140159886098896, "perf_period": 1, "common_type": 7229, "perf_pid": 21672, "common_pid": 21672, "common_flags": 0, "_probe_ret_ip": 4199308, "perf_ip": 4199308, "perf_id": 180213, "perf_callchain_size": 3, "perf_callchain": [18446744073709551104, 4199308, 4333543705419175690], "common_preempt_count": 0, "perf_tid": 21672}}, {"name": "dpu_load", "cat": "dpu", "pid": 21672, "tid": 21672, "ts": 4831326748.558, "ph": "B", "args": {"perf_period": 1, "common_type": 7214, "binary_path": 4207093, "perf_pid": 21672, "common_pid": 21672, "common_flags": 0, "dpu_set": 0, "perf_ip": 140159886095872, "perf_id": 179733, "_probe_ip": 140159886095872, "program": 0, "perf_callchain_size": 3, "perf_callchain": [18446744073709551104, 140159886095872, 4333543705419175690], "common_preempt_count": 0, "perf_tid": 21672}}, {"cat": "dpu", "pid": 21672, "tid": 21672, "ts": 4831371098.692, "ph": "E", "args": {"_probe_func": 140159886095872, "perf_period": 1, "common_type": 7215, "perf_pid": 21672, "common_pid": 21672, "common_flags": 0, "_probe_ret_ip": 4199575, "perf_ip": 4199575, "perf_id": 179765, "perf_callchain_size": 3, "perf_callchain": [18446744073709551104, 4199575, 4333543705419175690], "common_preempt_count": 0, "perf_tid": 21672}}, {"name": "dpu_push_xfer", "cat": "dpu", "pid": 21672, "tid": 21672, "ts": 4831377970.923, "ph": "B", "args": {"perf_period": 1, "symbol_name": 4207079, "common_type": 7234, "symbol_offset": 0, "perf_pid": 21672, "common_pid": 21672, "xfer": 0, "common_flags": 0, "dpu_set": 0, "perf_ip": 140159886114224, "perf_id": 180373, "_probe_ip": 140159886114224, "length": 2112, "perf_callchain_size": 4, "perf_callchain": [18446744073709551104, 140159886114224, 171798691880, 40], "common_preempt_count": 0, "flags": 0, "perf_tid": 21672}}, {"cat": "dpu", "pid": 21672, "tid": 21672, "ts": 4831394098.332, "ph": "E", "args": {"_probe_func": 140159886114224, "perf_period": 1, "common_type": 7235, "perf_pid": 21672, "common_pid": 21672, "common_flags": 0, "_probe_ret_ip": 4200214, "perf_ip": 4200214, "perf_id": 180405, "perf_callchain_size": 4, "perf_callchain": [18446744073709551104, 4200214, 171798691880, 40], "common_preempt_count": 0, "perf_tid": 21672}}, {"name": "dpu_push_xfer", "cat": "dpu", "pid": 21672, "tid": 21672, "ts": 4831394194.997, "ph": "B", "args": {"perf_period": 1, "symbol_name": 4207083, "common_type": 7234, "symbol_offset": 0, "perf_pid": 21672, "common_pid": 21672, "xfer": 0, "common_flags": 0, "dpu_set": 0, "perf_ip": 140159886114224, "perf_id": 180373, "_probe_ip": 140159886114224, "length": 45056, "perf_callchain_size": 4, "perf_callchain": [18446744073709551104, 140159886114224, 171798691880, 40], "common_preempt_count": 0, "flags": 0, "perf_tid": 21672}}, {"cat": "dpu", "pid": 21672, "tid": 21672, "ts": 4831642119.241, "ph": "E", "args": {"_probe_func": 140159886114224, "perf_period": 1, "common_type": 7235, "perf_pid": 21672, "common_pid": 21672, "common_flags": 0, "_probe_ret_ip": 4200374, "perf_ip": 4200374, "perf_id": 180405, "perf_callchain_size": 4, "perf_callchain": [18446744073709551104, 4200374, 171798691880, 40], "common_preempt_count": 0, "perf_tid": 21672}}, {"name": "dpu_launch", "cat": "dpu", "pid": 21672, "tid": 21672, "ts": 4831642126.935, "ph": "B", "args": {"perf_period": 1, "common_type": 7220, "perf_pid": 21672, "common_pid": 21672, "common_flags": 0, "dpu_set": 140159869050896, "perf_ip": 140159886096000, "perf_id": 179925, "_probe_ip": 140159886096000, "perf_callchain_size": 4, "perf_callchain": [18446744073709551104, 140159886096000, 171798691880, 40], "common_preempt_count": 0, "perf_tid": 21672, "policy": 1}}, {"cat": "dpu", "pid": 21672, "tid": 21672, "ts": 4831669989.544, "ph": "E", "args": {"_probe_func": 140159886096000, "perf_period": 1, "common_type": 7221, "perf_pid": 21672, "common_pid": 21672, "common_flags": 0, "_probe_ret_ip": 4200409, "perf_ip": 4200409, "perf_id": 179957, "perf_callchain_size": 4, "perf_callchain": [18446744073709551104, 4200409, 171798691880, 40], "common_preempt_count": 0, "perf_tid": 21672}}, {"name": "dpu_push_xfer", "cat": "dpu", "pid": 21672, "tid": 21672, "ts": 4831670236.671, "ph": "B", "args": {"perf_period": 1, "symbol_name": 4207088, "common_type": 7234, "symbol_offset": 0, "perf_pid": 21672, "common_pid": 21672, "xfer": 1, "common_flags": 0, "dpu_set": 0, "perf_ip": 140159886114224, "perf_id": 180373, "_probe_ip": 140159886114224, "length": 768, "perf_callchain_size": 4, "perf_callchain": [18446744073709551104, 140159886114224, 171798691880, 40], "common_preempt_count": 0, "flags": 0, "perf_tid": 21672}}, {"cat": "dpu", "pid": 21672, "tid": 21672, "ts": 4831677684.787, "ph": "E", "args": {"_probe_func": 140159886114224, "perf_period": 1, "common_type": 7235, "perf_pid": 21672, "common_pid": 21672, "common_flags": 0, "_probe_ret_ip": 4200596, "perf_ip": 4200596, "perf_id": 180405, "perf_callchain_size": 4, "perf_callchain": [18446744073709551104, 4200596, 171798691880, 40], "common_preempt_count": 0, "perf_tid": 21672}}, {"name": "dpu_load", "cat": "dpu", "pid": 21672, "tid": 21672, "ts": 4831797636.871, "ph": "B", "args": {"perf_period": 1, "common_type": 7214, "binary_path": 4207113, "perf_pid": 21672, "common_pid": 21672, "common_flags": 0, "dpu_set": 0, "perf_ip": 140159886095872, "perf_id": 179733, "_probe_ip": 140159886095872, "program": 0, "perf_callchain_size": 3, "perf_callchain": [18446744073709551104, 140159886095872, 4333543705419175690], "common_preempt_count": 0, "perf_tid": 21672}}, {"cat": "dpu", "pid": 21672, "tid": 21672, "ts": 4831822959.987, "ph": "E", "args": {"_probe_func": 140159886095872, "perf_period": 1, "common_type": 7215, "perf_pid": 21672, "common_pid": 21672, "common_flags": 0, "_probe_ret_ip": 4201383, "perf_ip": 4201383, "perf_id": 179765, "perf_callchain_size": 3, "perf_callchain": [18446744073709551104, 4201383, 4333543705419175690], "common_preempt_count": 0, "perf_tid": 21672}}, {"name": "dpu_push_xfer", "cat": "dpu", "pid": 21672, "tid": 21672, "ts": 4831826846.12, "ph": "B", "args": {"perf_period": 1, "symbol_name": 4207088, "common_type": 7234, "symbol_offset": 0, "perf_pid": 21672, "common_pid": 21672, "xfer": 0, "common_flags": 0, "dpu_set": 0, "perf_ip": 140159886114224, "perf_id": 180373, "_probe_ip": 140159886114224, "length": 768, "perf_callchain_size": 4, "perf_callchain": [18446744073709551104, 140159886114224, 171798691880, 40], "common_preempt_count": 0, "flags": 0, "perf_tid": 21672}}, {"cat": "dpu", "pid": 21672, "tid": 21672, "ts": 4831833170.65, "ph": "E", "args": {"_probe_func": 140159886114224, "perf_period": 1, "common_type": 7235, "perf_pid": 21672, "common_pid": 21672, "common_flags": 0, "_probe_ret_ip": 4201990, "perf_ip": 4201990, "perf_id": 180405, "perf_callchain_size": 4, "perf_callchain": [18446744073709551104, 4201990, 171798691880, 40], "common_preempt_count": 0, "perf_tid": 21672}}, {"name": "dpu_push_xfer", "cat": "dpu", "pid": 21672, "tid": 21672, "ts": 4831833250.045, "ph": "B", "args": {"perf_period": 1, "symbol_name": 4207103, "common_type": 7234, "symbol_offset": 0, "perf_pid": 21672, "common_pid": 21672, "xfer": 0, "common_flags": 0, "dpu_set": 0, "perf_ip": 140159886114224, "perf_id": 180373, "_probe_ip": 140159886114224, "length": 16384, "perf_callchain_size": 4, "perf_callchain": [18446744073709551104, 140159886114224, 171798691880, 40], "common_preempt_count": 0, "flags": 0, "perf_tid": 21672}}, {"cat": "dpu", "pid": 21672, "tid": 21672, "ts": 4831928324.774, "ph": "E", "args": {"_probe_func": 140159886114224, "perf_period": 1, "common_type": 7235, "perf_pid": 21672, "common_pid": 21672, "common_flags": 0, "_probe_ret_ip": 4202150, "perf_ip": 4202150, "perf_id": 180405, "perf_callchain_size": 4, "perf_callchain": [18446744073709551104, 4202150, 171798691880, 40], "common_preempt_count": 0, "perf_tid": 21672}}, {"name": "dpu_launch", "cat": "dpu", "pid": 21672, "tid": 21672, "ts": 4831928327.622, "ph": "B", "args": {"perf_period": 1, "common_type": 7220, "perf_pid": 21672, "common_pid": 21672, "common_flags": 0, "dpu_set": 140159867097104, "perf_ip": 140159886096000, "perf_id": 179925, "_probe_ip": 140159886096000, "perf_callchain_size": 4, "perf_callchain": [18446744073709551104, 140159886096000, 171798691880, 40], "common_preempt_count": 0, "perf_tid": 21672, "policy": 1}}, {"cat": "dpu", "pid": 21672, "tid": 21672, "ts": 4831937250.988, "ph": "E", "args": {"_probe_func": 140159886096000, "perf_period": 1, "common_type": 7221, "perf_pid": 21672, "common_pid": 21672, "common_flags": 0, "_probe_ret_ip": 4202185, "perf_ip": 4202185, "perf_id": 179957, "perf_callchain_size": 4, "perf_callchain": [18446744073709551104, 4202185, 171798691880, 40], "common_preempt_count": 0, "perf_tid": 21672}}, {"name": "dpu_push_xfer", "cat": "dpu", "pid": 21672, "tid": 21672, "ts": 4831937327.905, "ph": "B", "args": {"perf_period": 1, "symbol_name": 4207108, "common_type": 7234, "symbol_offset": 0, "perf_pid": 21672, "common_pid": 21672, "xfer": 1, "common_flags": 0, "dpu_set": 0, "perf_ip": 140159886114224, "perf_id": 180373, "_probe_ip": 140159886114224, "length": 768, "perf_callchain_size": 4, "perf_callchain": [18446744073709551104, 140159886114224, 171798691880, 40], "common_preempt_count": 0, "flags": 0, "perf_tid": 21672}}, {"cat": "dpu", "pid": 21672, "tid": 21672, "ts": 4831943262.798, "ph": "E", "args": {"_probe_func": 140159886114224, "perf_period": 1, "common_type": 7235, "perf_pid": 21672, "common_pid": 21672, "common_flags": 0, "_probe_ret_ip": 4202372, "perf_ip": 4202372, "perf_id": 180405, "perf_callchain_size": 4, "perf_callchain": [18446744073709551104, 4202372, 171798691880, 40], "common_preempt_count": 0, "perf_tid": 21672}}, {"name": "dpu_load", "cat": "dpu", "pid": 21672, "tid": 21672, "ts": 4832052260.214, "ph": "B", "args": {"perf_period": 1, "common_type": 7214, "binary_path": 4207136, "perf_pid": 21672, "common_pid": 21672, "common_flags": 0, "dpu_set": 0, "perf_ip": 140159886095872, "perf_id": 179734, "_probe_ip": 140159886095872, "program": 0, "perf_callchain_size": 3, "perf_callchain": [18446744073709551104, 140159886095872, 6075149511265903986], "common_preempt_count": 0, "perf_tid": 21672}}, {"cat": "dpu", "pid": 21672, "tid": 21672, "ts": 4832057477.334, "ph": "E", "args": {"_probe_func": 140159886095872, "perf_period": 1, "common_type": 7215, "perf_pid": 21672, "common_pid": 21672, "common_flags": 0, "_probe_ret_ip": 4203159, "perf_ip": 4203159, "perf_id": 179766, "perf_callchain_size": 3, "perf_callchain": [18446744073709551104, 4203159, 6075149511265903986], "common_preempt_count": 0, "perf_tid": 21672}}, {"name": "dpu_push_xfer", "cat": "dpu", "pid": 21672, "tid": 21672, "ts": 4832058772.989, "ph": "B", "args": {"perf_period": 1, "symbol_name": 4207108, "common_type": 7234, "symbol_offset": 0, "perf_pid": 21672, "common_pid": 21672, "xfer": 0, "common_flags": 0, "dpu_set": 0, "perf_ip": 140159886114224, "perf_id": 180374, "_probe_ip": 140159886114224, "length": 768, "perf_callchain_size": 4, "perf_callchain": [18446744073709551104, 140159886114224, 171798691880, 40], "common_preempt_count": 0, "flags": 0, "perf_tid": 21672}}, {"cat": "dpu", "pid": 21672, "tid": 21672, "ts": 4832068430.13, "ph": "E", "args": {"_probe_func": 140159886114224, "perf_period": 1, "common_type": 7235, "perf_pid": 21672, "common_pid": 21672, "common_flags": 0, "_probe_ret_ip": 4203643, "perf_ip": 4203643, "perf_id": 180406, "perf_callchain_size": 4, "perf_callchain": [18446744073709551104, 4203643, 171798691880, 40], "common_preempt_count": 0, "perf_tid": 21672}}, {"name": "dpu_push_xfer", "cat": "dpu", "pid": 21672, "tid": 21672, "ts": 4832068540.424, "ph": "B", "args": {"perf_period": 1, "symbol_name": 4207124, "common_type": 7234, "symbol_offset": 0, "perf_pid": 21672, "common_pid": 21672, "xfer": 0, "common_flags": 0, "dpu_set": 0, "perf_ip": 140159886114224, "perf_id": 180374, "_probe_ip": 140159886114224, "length": 256, "perf_callchain_size": 4, "perf_callchain": [18446744073709551104, 140159886114224, 171798691880, 40], "common_preempt_count": 0, "flags": 0, "perf_tid": 21672}}, {"cat": "dpu", "pid": 21672, "tid": 21672, "ts": 4832071866.028, "ph": "E", "args": {"_probe_func": 140159886114224, "perf_period": 1, "common_type": 7235, "perf_pid": 21672, "common_pid": 21672, "common_flags": 0, "_probe_ret_ip": 4203819, "perf_ip": 4203819, "perf_id": 180406, "perf_callchain_size": 4, "perf_callchain": [18446744073709551104, 4203819, 171798691880, 40], "common_preempt_count": 0, "perf_tid": 21672}}, {"name": "dpu_launch", "cat": "dpu", "pid": 21672, "tid": 21672, "ts": 4832071868.393, "ph": "B", "args": {"perf_period": 1, "common_type": 7220, "perf_pid": 21672, "common_pid": 21672, "common_flags": 0, "dpu_set": 4976544, "perf_ip": 140159886096000, "perf_id": 179926, "_probe_ip": 140159886096000, "perf_callchain_size": 4, "perf_callchain": [18446744073709551104, 140159886096000, 171798691880, 40], "common_preempt_count": 0, "perf_tid": 21672, "policy": 1}}, {"cat": "dpu", "pid": 21672, "tid": 21672, "ts": 4832073955.0, "ph": "E", "args": {"_probe_func": 140159886096000, "perf_period": 1, "common_type": 7221, "perf_pid": 21672, "common_pid": 21672, "common_flags": 0, "_probe_ret_ip": 4203853, "perf_ip": 4203853, "perf_id": 179958, "perf_callchain_size": 4, "perf_callchain": [18446744073709551104, 4203853, 171798691880, 40], "common_preempt_count": 0, "perf_tid": 21672}}, {"name": "dpu_push_xfer", "cat": "dpu", "pid": 21672, "tid": 21672, "ts": 4832074049.854, "ph": "B", "args": {"perf_period": 1, "symbol_name": 4207129, "common_type": 7234, "symbol_offset": 0, "perf_pid": 21672, "common_pid": 21672, "xfer": 1, "common_flags": 0, "dpu_set": 0, "perf_ip": 140159886114224, "perf_id": 180374, "_probe_ip": 140159886114224, "length": 12, "perf_callchain_size": 4, "perf_callchain": [18446744073709551104, 140159886114224, 171798691880, 40], "common_preempt_count": 0, "flags": 0, "perf_tid": 21672}}, {"cat": "dpu", "pid": 21672, "tid": 21672, "ts": 4832074411.886, "ph": "E", "args": {"_probe_func": 140159886114224, "perf_period": 1, "common_type": 7235, "perf_pid": 21672, "common_pid": 21672, "common_flags": 0, "_probe_ret_ip": 4204038, "perf_ip": 4204038, "perf_id": 180406, "perf_callchain_size": 4, "perf_callchain": [18446744073709551104, 4204038, 171798691880, 40], "common_preempt_count": 0, "perf_tid": 21672}}]}